LICENSE
README.md
setup.py
Cloud/Messaging.py
Cloud/__init__.py
robloxcloud.egg-info/PKG-INFO
robloxcloud.egg-info/SOURCES.txt
robloxcloud.egg-info/dependency_links.txt
robloxcloud.egg-info/top_level.txt